<?xml version="1.0"?>
<?xml-stylesheet type="text/xsl" href="billres.xsl"?>
<!DOCTYPE bill PUBLIC "-//US Congress//DTDs/bill.dtd//EN" "bill.dtd">
<bill bill-stage="Referred-in-Senate" bill-type="olc" dms-id="H7E6983582EC346CAB3DDB15B48D086AE" key="H" public-private="public">
<metadata xmlns:dc="http://purl.org/dc/elements/1.1/">
<dublinCore>
<dc:title>110 HR 513 : National Heroes Credit Protection
</dc:title>
<dc:publisher>U.S. House of Representatives</dc:publisher>
<dc:date>2007-11-06</dc:date>
<dc:format>text/xml</dc:format>
<dc:language>EN</dc:language>
<dc:rights>Pursuant to Title 17 Section 105 of the United States Code, this file is not subject to copyright protection and is in the public domain.</dc:rights>
</dublinCore>
</metadata>
	<form>
		<distribution-code display="yes">IIB</distribution-code>
		<congress>110th CONGRESS</congress>
		<session>1st Session</session>
		<legis-num>H. R. 513</legis-num>
		<current-chamber display="yes">IN THE SENATE OF THE UNITED
		  STATES</current-chamber>
		<action>
			<action-date date="20071106">November 6, 2007</action-date>
			<action-desc>Received; read twice and referred to the
			 <committee-name committee-id="SSVA00">Committee on Veterans'
			 Affairs</committee-name></action-desc>
		</action>
		<legis-type>AN ACT</legis-type>
		<official-title display="yes">To amend the Servicemembers Civil Relief
		  Act to enhance the protection of credit ratings of members of the reserve
		  component who serve on active duty in support of a contingency operation, and
		  for other purposes.</official-title>
	</form>
	<legis-body id="H93C7E2F2B91E403D9DC77C9D22C53854" style="OLC">
		<section id="H07DA2508F93F4DB8BACC94A2F9C19700" section-type="section-one"><enum>1.</enum><header>Short title</header><text display-inline="no-display-inline">This Act may be cited as the
			 <quote><short-title>National Heroes Credit Protection
			 Act</short-title></quote>.</text>
		</section><section id="HCB548AC8B27D45C7B5A24919C200A2D8"><enum>2.</enum><header>Protection of
			 credit ratings of members of the reserve components deployed in support of
			 contingency operations</header>
			<subsection id="H89E2EF3630D249D0A5585ECEDD660029"><enum>(a)</enum><header>In
			 general</header><text>Title II of the Servicemembers Civil Relief Act (50
			 U.S.C. App. 521 et seq.) is amended by adding at the end the following new
			 section:</text>
				<quoted-block display-inline="no-display-inline" id="HC9891AB7FBFC46A8AD1CC8F798C595D2" style="OLC">
					<section id="H132E373310AE4DBAA9C8A6EB9CE25B3C"><enum>208.</enum><header>Protection of
				credit ratings of members of reserve components deployed in support of
				contingency operations</header>
						<subsection id="HEFA73CF83E8045F09C9836B82C83B3D"><enum>(a)</enum><header>Request for
				military service deployment explanation</header><text display-inline="yes-display-inline">At any time during or after serving on
				active duty in support of a contingency operation, an eligible servicemember
				may request that a consumer reporting agency include a military service
				deployment explanation with respect to a qualifying account in the file of that
				servicemember at the consumer reporting agency.</text>
						</subsection><subsection id="HD8D76A2B072C4611BF027FE66FEFC97"><enum>(b)</enum><header>Responsibilities
				of consumer reporting agencies</header><text>Upon receiving a request from an
				eligible servicemember under subsection (a), a consumer reporting agency
				shall—</text>
							<paragraph id="HDF7C20D54A7844CE92BE87C25D00DA8"><enum>(1)</enum><text>include a military
				service deployment explanation with respect to a qualifying account in the file
				of that servicemember and provide the military service deployment explanation
				to each person who requests the credit score or consumer report of the
				servicemember;</text>
							</paragraph><paragraph id="H3BBE9247EA1B4D50A47004F31EDED7F7"><enum>(2)</enum><text>develop and
				maintain procedures for the referral to other such agencies of any military
				service deployment explanation received by the agency; and</text>
							</paragraph><paragraph id="H778B928BCD574A0ABE786752A77B001F"><enum>(3)</enum><text>notify the
				servicemember in writing that the inclusion of any explanation or notation in
				the file of the servicemember could potentially negatively affect the credit
				rating of the servicemember and may not mitigate a low credit score.</text>
							</paragraph></subsection><subsection id="HE2C583CAEAAA42E7BAF9C000002BD25"><enum>(c)</enum><header>Duty of reseller
				to reconvey military service deployment explanation</header><text>A reseller
				shall include in any report of the reseller on a servicemember any military
				service deployment explanation placed in the file of that servicemember by
				another consumer reporting agency pursuant to this section.</text>
						</subsection><subsection id="H0024B03D0E894B6AA82C802BA79BEDA0"><enum>(d)</enum><header>Acknowledgment
				of military service deployment explanation</header><text>Any prospective user
				of a consumer credit report containing a military service deployment
				explanation shall acknowledge such military service deployment
				explanation.</text>
						</subsection><subsection id="H3701DC0AE33444DF8089AA73685DA9D"><enum>(e)</enum><header>Definitions</header><text>For
				the purposes of this section:</text>
							<paragraph id="H0741760A98A841BE8958C7DAA1C2BE9B"><enum>(1)</enum><text display-inline="yes-display-inline">The term <quote>eligible
				servicemember</quote> means a member of a reserve component who serves on
				active duty outside the continental United States in support of a contingency
				operation under a call or order specifying a period of such service of not less
				than 180 days (or who enters such service under a call or order specifying a
				period of 180 days or less and who, without a break in service, receives orders
				extending the period of such service to a period of not less than 180
				days).</text>
							</paragraph><paragraph id="H0446F4A6E86742E2AA06F773D769DAE"><enum>(2)</enum><text>The term
				<quote>military service deployment explanation</quote> means a code generated
				by a consumer reporting agency that is delivered in conjunction with a consumer
				report or credit score to a user of the consumer report or credit score to
				indicate that the consumer report or credit score of the consumer was adversely
				affected during a period in which the consumer was a servicemember serving on
				active duty outside the continental United States in support of a contingency
				operation.</text>
							</paragraph><paragraph id="H3A7A07787D854CD587CC933BEBDA1155"><enum>(3)</enum><text>The term
				<quote>contingency operation</quote> has the meaning given that term under
				section
				101(a)(13) of title 10, United States Code.</text>
							</paragraph><paragraph id="H073A339ABC124C76B9F03D39D2A29BFB"><enum>(4)</enum><text display-inline="yes-display-inline">The term <quote>active duty</quote> has the
				meaning given that term under
				section
				101(d)(1) of title 10, United States Code.</text>
							</paragraph><paragraph id="H701B5354556A4918BA76FDE02E17AD44"><enum>(5)</enum><text>The term
				<quote>consumer reporting agency</quote> has the meaning given that term under
				section 603 of the Fair Credit Reporting Act.</text>
							</paragraph><paragraph id="H601EBB8C40C34EE8803C1B208B0004EF"><enum>(6)</enum><text>The term
				<quote>reseller</quote> has the meaning given that term under section 603 of
				the Fair Credit Reporting Act.</text>
							</paragraph><paragraph id="H08EF60AFCBAE492DB98DCD70714F7D40"><enum>(7)</enum><text>The term
				<quote>qualifying account</quote> means an account that was opened by a
				servicemember before the date on which the servicemember was deployed outside
				the continental United States in support of a contingency operation, but only
				with respect to obligations incurred before such
				date.</text>
							</paragraph></subsection></section><after-quoted-block>.</after-quoted-block></quoted-block>
			</subsection><subsection id="H4C8726636FE644AD8808A2BD0041CF93"><enum>(b)</enum><header>Clerical
			 amendment</header><text display-inline="yes-display-inline">The table of
			 contents in section 1(b) of such Act is amended by inserting after the item
			 relating to section 207 the following new item:</text>
				<quoted-block display-inline="no-display-inline" id="HCC06556844AC417AAEC988AD2F008563" style="OLC">
					<toc regeneration="no-regeneration">
						<toc-entry level="section">Sec. 208. Protection of credit ratings of
				certain
				servicemembers.</toc-entry>
					</toc>
					<after-quoted-block>.</after-quoted-block></quoted-block>
			</subsection><subsection id="H2D118717CEA941BAB605B6004FB4EC5F"><enum>(c)</enum><header>Military service
			 deployment explanation not to affect certain future
			 transactions</header><text>Section 108 of such Act (50 U.S.C. App.
			 518) is amended in the matter preceding paragraph (1), by
			 inserting after <quote>liability of that servicemember</quote> the following:
			 <quote>, or the inclusion of a military service deployment explanation in a
			 file of the servicemember at a consumer reporting agency pursuant to section
			 208,</quote>.</text>
			</subsection></section></legis-body>
	<attestation>
		<attestation-group>
			<attestation-date chamber="House" date="20071105">Passed the House of
			 Representatives November 5, 2007.</attestation-date>
			<attestor display="yes">Lorraine C. Miller,</attestor>
			<role>Clerk</role>
		</attestation-group>
	</attestation>
</bill>


